AUTHORS
CHANGES.rst
LICENSE
MANIFEST.in
README.rst
setup.cfg
setup.py
src/django_page_components.egg-info/PKG-INFO
src/django_page_components.egg-info/SOURCES.txt
src/django_page_components.egg-info/dependency_links.txt
src/django_page_components.egg-info/requires.txt
src/django_page_components.egg-info/top_level.txt
src/page_components/__init__.py
src/page_components/page_component.py
src/page_components/views.py