Metadata-Version: 2.1
Name: django-page-components
Version: 1.0.0
Summary: Mini-framework for creating re-usable UI components for Django
Home-page: https://github.com/andreyfedoseev/django-page-components
Author: Andrey Fedoseev
Author-email: andrey.fedoseev@gmail.com
License: UNKNOWN
Keywords: django
Platform: UNKNOWN
Classifier: Development Status :: 4 - Beta
Classifier: Framework :: Django
Classifier: Intended Audience :: Developers
Classifier: License :: OSI Approved :: BSD License
Classifier: Operating System :: OS Independent
Classifier: Programming Language :: Python
Classifier: Programming Language :: Python :: 3
Classifier: Topic :: Internet :: WWW/HTTP
Requires-Python: >=3.6
License-File: LICENSE
License-File: AUTHORS
